aclib/inputs/__init__.py
aclib/inputs/__API__/inputs.py
aclib.inputs-1.0.0.dist-info/LICENSE
aclib.inputs-1.0.0.dist-info/METADATA
aclib.inputs-1.0.0.dist-info/WHEEL
aclib.inputs-1.0.0.dist-info/top_level.txt
aclib.inputs-1.0.0.dist-info/RECORD
